{
    "asset": {
        "version": "0.0"
    },
    "geometricError": 4.0,
    "root": {
        "boundingVolume": {
            "sphere": [
                -2498.0728913,
                504.365282609,
                8.87291900785,
                12.103647684601996
            ]
        },
        "refine": "replace",
        "geometricError": 2.0,
        "content": {
            "url": "tile_4_28_26_tex.b3dm"
        },
        "children": [
            {
                "boundingVolume": {
                    "sphere": [
                        -2501.9791413042,
                        500.4590326087,
                        6.38059898895,
                        5.987190883019932
                    ]
                },
                "geometricError": 1.0,
                "content": {
                    "url": "tile_5_28_26_tex.b3dm"
                }
            },
            {
                "boundingVolume": {
                    "sphere": [
                        -2501.9791413042,
                        508.2715326087,
                        8.8576714952,
                        7.422702069640117
                    ]
                },
                "geometricError": 1.0,
                "content": {
                    "url": "tile_5_28_27_tex.b3dm"
                }
            },
            {
                "boundingVolume": {
                    "sphere": [
                        -2494.1666413042,
                        500.4590326087,
                        6.492743754,
                        6.009256127037433
                    ]
                },
                "geometricError": 1.0,
                "content": {
                    "url": "tile_5_29_26_tex.b3dm"
                }
            },
            {
                "boundingVolume": {
                    "sphere": [
                        -2494.1666413042,
                        508.2715326087,
                        4.85674776195,
                        5.565427786960704
                    ]
                },
                "geometricError": 1.0,
                "content": {
                    "url": "tile_5_29_27_tex.b3dm"
                }
            }
        ]
    }
}