{
    "asset": {
        "version": "0.0"
    },
    "geometricError": 4.0,
    "root": {
        "boundingVolume": {
            "sphere": [
                -2529.3228913,
                535.615282609,
                93.39298119224999,
                90.38188540604287
            ]
        },
        "refine": "replace",
        "geometricError": 2.0,
        "content": {
            "url": "tile_4_24_30_tex.b3dm"
        },
        "children": [
            {
                "boundingVolume": {
                    "sphere": [
                        -2533.2291413042,
                        531.7090326087,
                        88.449435603,
                        84.96850107400209
                    ]
                },
                "geometricError": 1.0,
                "content": {
                    "url": "tile_5_24_30_tex.b3dm"
                }
            },
            {
                "boundingVolume": {
                    "sphere": [
                        -2533.2291413042,
                        539.5215326087,
                        92.54819206825,
                        88.0662594790354
                    ]
                },
                "geometricError": 1.0,
                "content": {
                    "url": "tile_5_24_31_tex.b3dm"
                }
            },
            {
                "boundingVolume": {
                    "sphere": [
                        -2525.4166413042,
                        531.7090326087,
                        90.85003250945,
                        86.70214777752052
                    ]
                },
                "geometricError": 1.0,
                "content": {
                    "url": "tile_5_25_30_tex.b3dm"
                }
            },
            {
                "boundingVolume": {
                    "sphere": [
                        -2525.4166413042,
                        539.52153260865,
                        93.87663275599999,
                        89.3912489844813
                    ]
                },
                "geometricError": 1.0,
                "content": {
                    "url": "tile_5_25_31_tex.b3dm"
                }
            }
        ]
    }
}