{
    "asset": {
        "version": "0.0"
    },
    "geometricError": 4.0,
    "root": {
        "boundingVolume": {
            "sphere": [
                -2513.6978913,
                410.615282609,
                44.2059437931,
                41.53867676363929
            ]
        },
        "refine": "replace",
        "geometricError": 2.0,
        "content": {
            "url": "tile_4_26_14_tex.b3dm"
        },
        "children": [
            {
                "boundingVolume": {
                    "sphere": [
                        -2517.6041413042,
                        406.7090326087,
                        7.5269847704499999,
                        6.4681196905993609
                    ]
                },
                "geometricError": 1.0,
                "content": {
                    "url": "tile_5_26_14_tex.b3dm"
                }
            },
            {
                "boundingVolume": {
                    "sphere": [
                        -2517.6041413042,
                        414.5215326087,
                        39.571511818,
                        31.656575096903219
                    ]
                },
                "geometricError": 1.0,
                "content": {
                    "url": "tile_5_26_15_tex.b3dm"
                }
            },
            {
                "boundingVolume": {
                    "sphere": [
                        -2509.7916413042,
                        406.7090326087,
                        8.0768103095,
                        6.692236573438067
                    ]
                },
                "geometricError": 1.0,
                "content": {
                    "url": "tile_5_27_14_tex.b3dm"
                }
            },
            {
                "boundingVolume": {
                    "sphere": [
                        -2509.7916413042,
                        414.5215326087,
                        46.635744511000009,
                        38.0160874910814
                    ]
                },
                "geometricError": 1.0,
                "content": {
                    "url": "tile_5_27_15_tex.b3dm"
                }
            }
        ]
    }
}