{
    "asset": {
        "version": "0.0"
    },
    "geometricError": 4.0,
    "root": {
        "boundingVolume": {
            "sphere": [
                -2638.6978913,
                332.490282609,
                57.723146170999999,
                39.95261110830341
            ]
        },
        "refine": "replace",
        "geometricError": 2.0,
        "content": {
            "url": "tile_4_10_4_tex.b3dm"
        },
        "children": [
            {
                "boundingVolume": {
                    "sphere": [
                        -2642.6041413042,
                        328.5840326087,
                        23.772330461099999,
                        6.970587617964588
                    ]
                },
                "geometricError": 1.0,
                "content": {
                    "url": "tile_5_10_4_tex.b3dm"
                }
            },
            {
                "boundingVolume": {
                    "sphere": [
                        -2642.6041413042,
                        336.3965326087,
                        20.598016577000004,
                        5.638015039068665
                    ]
                },
                "geometricError": 1.0,
                "content": {
                    "url": "tile_5_10_5_tex.b3dm"
                }
            },
            {
                "boundingVolume": {
                    "sphere": [
                        -2634.7916413042,
                        328.5840326087,
                        57.8066567315,
                        38.706148438087257
                    ]
                },
                "geometricError": 1.0,
                "content": {
                    "url": "tile_5_11_4_tex.b3dm"
                }
            },
            {
                "boundingVolume": {
                    "sphere": [
                        -2634.7916413042,
                        336.3965326087,
                        20.5214231825,
                        5.6495664928579318
                    ]
                },
                "geometricError": 1.0,
                "content": {
                    "url": "tile_5_11_5_tex.b3dm"
                }
            }
        ]
    }
}