{
    "asset": {
        "version": "0.0"
    },
    "geometricError": 4.0,
    "root": {
        "boundingVolume": {
            "sphere": [
                -2669.9478913,
                316.865282609,
                98.0610816669,
                68.54924789138748
            ]
        },
        "refine": "replace",
        "geometricError": 2.0,
        "content": {
            "url": "tile_4_6_2_tex.b3dm"
        },
        "children": [
            {
                "boundingVolume": {
                    "sphere": [
                        -2673.8541413042,
                        312.9590326087,
                        95.29686584745,
                        64.35164025276615
                    ]
                },
                "geometricError": 1.0,
                "content": {
                    "url": "tile_5_6_2_tex.b3dm"
                }
            },
            {
                "boundingVolume": {
                    "sphere": [
                        -2673.8541413042,
                        320.7715326087,
                        162.1023828059,
                        6.60015017121783
                    ]
                },
                "geometricError": 1.0,
                "content": {
                    "url": "tile_5_6_3_tex.b3dm"
                }
            },
            {
                "boundingVolume": {
                    "sphere": [
                        -2666.0416413042,
                        312.9590326087,
                        94.84480754764999,
                        64.67309992351848
                    ]
                },
                "geometricError": 1.0,
                "content": {
                    "url": "tile_5_7_2_tex.b3dm"
                }
            },
            {
                "boundingVolume": {
                    "sphere": [
                        -2666.0416413042,
                        320.7715326087,
                        96.971032846,
                        65.95782897843739
                    ]
                },
                "geometricError": 1.0,
                "content": {
                    "url": "tile_5_7_3_tex.b3dm"
                }
            }
        ]
    }
}